setup.py
wayround_org/carafe/__init__.py
wayround_org/carafe/carafe.py
wayround_org_carafe.egg-info/PKG-INFO
wayround_org_carafe.egg-info/SOURCES.txt
wayround_org_carafe.egg-info/dependency_links.txt
wayround_org_carafe.egg-info/requires.txt
wayround_org_carafe.egg-info/top_level.txt