Metadata-Version: 1.1
Name: wayround-org-carafe
Version: 0.4
Summary: micro web-framefork for wsgi
Home-page: https://github.com/AnimusPEXUS/wayround_org_carafe
Author: Alexey Gorshkov
Author-email: animus@wayround.org
License: UNKNOWN
Platform: UNKNOWN
Classifier: License :: OSI Approved :: GNU General Public License v3 or later (GPLv3+)
